[
  {
    "name": "noticias",
    "language": "es",
    "data": {
      "title": "Noticias",
      "news": [
        {
          "team": "Actres",
          "text": "Donec id elit non mi porta gravida at eget metus. Fusce dapibus, tellus ac cursus commodo, tortor mauris condimentum nibh, ut fermentum massa justo sit amet risus.",
          "link": "http://www.google.es"
        },
        {
          "team": "Actres",
          "text": "Donec id elit non mi porta gravida at eget metus. Fusce dapibus, tellus ac cursus commodo, tortor mauris condimentum nibh, ut fermentum massa justo sit amet risus.",
          "link": "http://www.google.es"
        },
        {
          "team": "Actres",
          "text": "Donec id elit non mi porta gravida at eget metus. Fusce dapibus, tellus ac cursus commodo, tortor mauris condimentum nibh, ut fermentum massa justo sit amet risus.",
          "link": "http://www.google.es"
        },
        {
          "team": "Actres",
          "text": "Donec id elit non mi porta gravida at eget metus. Fusce dapibus, tellus ac cursus commodo, tortor mauris condimentum nibh, ut fermentum massa justo sit amet risus.",
          "link": "http://www.google.es"
        },
        {
          "team": "Actres",
          "text": "Donec id elit non mi porta gravida at eget metus. Fusce dapibus, tellus ac cursus commodo, tortor mauris condimentum nibh, ut fermentum massa justo sit amet risus.",
          "link": "http://www.google.es"
        },
        {
          "team": "Actres",
          "text": "Donec id elit non mi porta gravida at eget metus. Fusce dapibus, tellus ac cursus commodo, tortor mauris condimentum nibh, ut fermentum massa justo sit amet risus.",
          "link": "http://www.google.es"
        },
        {
          "team": "Actres",
          "text": "Donec id elit non mi porta gravida at eget metus. Fusce dapibus, tellus ac cursus commodo, tortor mauris condimentum nibh, ut fermentum massa justo sit amet risus.",
          "link": "http://www.google.es"
        },
        {
          "team": "Actres",
          "text": "Donec id elit non mi porta gravida at eget metus. Fusce dapibus, tellus ac cursus commodo, tortor mauris condimentum nibh, ut fermentum massa justo sit amet risus.",
          "link": "http://www.google.es"
        },
        {
          "team": "Actres",
          "text": "Donec id elit non mi porta gravida at eget metus. Fusce dapibus, tellus ac cursus commodo, tortor mauris condimentum nibh, ut fermentum massa justo sit amet risus.",
          "link": "http://www.google.es"
        },
        {
          "team": "Actres",
          "text": "Donec id elit non mi porta gravida at eget metus. Fusce dapibus, tellus ac cursus commodo, tortor mauris condimentum nibh, ut fermentum massa justo sit amet risus.",
          "link": "http://www.google.es"
        },
        {
          "team": "Actres",
          "text": "Donec id elit non mi porta gravida at eget metus. Fusce dapibus, tellus ac cursus commodo, tortor mauris condimentum nibh, ut fermentum massa justo sit amet risus.",
          "link": "http://www.google.es"
        }
      ]
    }
  },
  {
    "name": "noticias",
    "language": "en",
    "data": {
      "title": "Noticias",
      "news": [
        {
          "team": "Actres",
          "text": "Donec id elit non mi porta gravida at eget metus. Fusce dapibus, tellus ac cursus commodo, tortor mauris condimentum nibh, ut fermentum massa justo sit amet risus.",
          "link": "http://www.google.es"
        },
        {
          "team": "Actres",
          "text": "Donec id elit non mi porta gravida at eget metus. Fusce dapibus, tellus ac cursus commodo, tortor mauris condimentum nibh, ut fermentum massa justo sit amet risus.",
          "link": "http://www.google.es"
        },
        {
          "team": "Actres",
          "text": "Donec id elit non mi porta gravida at eget metus. Fusce dapibus, tellus ac cursus commodo, tortor mauris condimentum nibh, ut fermentum massa justo sit amet risus.",
          "link": "http://www.google.es"
        },
        {
          "team": "Actres",
          "text": "Donec id elit non mi porta gravida at eget metus. Fusce dapibus, tellus ac cursus commodo, tortor mauris condimentum nibh, ut fermentum massa justo sit amet risus.",
          "link": "http://www.google.es"
        },
        {
          "team": "Actres",
          "text": "Donec id elit non mi porta gravida at eget metus. Fusce dapibus, tellus ac cursus commodo, tortor mauris condimentum nibh, ut fermentum massa justo sit amet risus.",
          "link": "http://www.google.es"
        },
        {
          "team": "Actres",
          "text": "Donec id elit non mi porta gravida at eget metus. Fusce dapibus, tellus ac cursus commodo, tortor mauris condimentum nibh, ut fermentum massa justo sit amet risus.",
          "link": "http://www.google.es"
        },
        {
          "team": "Actres",
          "text": "Donec id elit non mi porta gravida at eget metus. Fusce dapibus, tellus ac cursus commodo, tortor mauris condimentum nibh, ut fermentum massa justo sit amet risus.",
          "link": "http://www.google.es"
        },
        {
          "team": "Actres",
          "text": "Donec id elit non mi porta gravida at eget metus. Fusce dapibus, tellus ac cursus commodo, tortor mauris condimentum nibh, ut fermentum massa justo sit amet risus.",
          "link": "http://www.google.es"
        },
        {
          "team": "Actres",
          "text": "Donec id elit non mi porta gravida at eget metus. Fusce dapibus, tellus ac cursus commodo, tortor mauris condimentum nibh, ut fermentum massa justo sit amet risus.",
          "link": "http://www.google.es"
        },
        {
          "team": "Actres",
          "text": "Donec id elit non mi porta gravida at eget metus. Fusce dapibus, tellus ac cursus commodo, tortor mauris condimentum nibh, ut fermentum massa justo sit amet risus.",
          "link": "http://www.google.es"
        },
        {
          "team": "Actres",
          "text": "Donec id elit non mi porta gravida at eget metus. Fusce dapibus, tellus ac cursus commodo, tortor mauris condimentum nibh, ut fermentum massa justo sit amet risus.",
          "link": "http://www.google.es"
        }
      ]
    }
  }
]
